README.md
src/FinePy/Helper.py
src/FinePy/Log.py
src/FinePy/__init__.py
src/FinePy.egg-info/PKG-INFO
src/FinePy.egg-info/SOURCES.txt
src/FinePy.egg-info/dependency_links.txt
src/FinePy.egg-info/top_level.txt
src/FinePy/Cache/__init__.py
src/FinePy/ClickHouse/__init__.py
src/FinePy/Crypt/__init__.py
src/FinePy/Database/Db.py
src/FinePy/Database/Model.py
src/FinePy/Database/MySql.py
src/FinePy/Database/Orm.py
src/FinePy/Database/OrmFactory.py
src/FinePy/Database/__init__.py
src/FinePy/Exceptions/Assert.py
src/FinePy/Exceptions/__init__.py
src/FinePy/Facades/__init__.py
src/FinePy/File/Excel.py
src/FinePy/File/Report.py
src/FinePy/File/__init__.py
src/FinePy/Http/Request.py
src/FinePy/Http/__init__.py
src/FinePy/Protocol/Mail.py
src/FinePy/Protocol/__init__.py