Metadata-Version: 1.2
Name: FinePy
Version: 1.0.1
Summary: I'm Fine... 
Home-page: https://github.com/ClanceyHuang/FinePy
Author: ClanceyHuang
Author-email: ClanceyHuang@outlook.com
License: MIT Licence
Keywords: FinePy
Platform: any
Requires-Python: >=3.6.*
